{
  "$schema": "https://greenticai.github.io/greentic-component/schemas/v1/component.manifest.schema.json",
  "id": "ai.greentic.component-prompt2flow",
  "name": "component-prompt2flow",
  "version": "0.1.0",
  "world": "component",
  "describe_export": "describe",
  "default_operation": "handle_message",
  "operations": [
    {
      "name": "handle_message",
      "input_schema": "schemas/io/input.schema.json",
      "output_schema": "schemas/io/output.schema.json"
    }
  ],
  "capabilities": {
    "wasi": {
      "filesystem": {
        "mode": "read_only",
        "mounts": [
          { "guest_path": ".", "host_class": "workspace", "name": "workspace" }
        ]
      }
    }
  },
  "limits": {
    "memory_mb": 128,
    "wall_time_ms": 1000
  },
  "artifacts": {
    "component_wasm": "target/wasm32-wasip2/release/component_prompt2flow.wasm"
  },
  "hashes": {
    "component_wasm": "blake3:0000000000000000000000000000000000000000000000000000000000000000"
  }
}

